pulumi_checkly/__init__.py
pulumi_checkly/_inputs.py
pulumi_checkly/_utilities.py
pulumi_checkly/alert_channel.py
pulumi_checkly/check.py
pulumi_checkly/check_group.py
pulumi_checkly/client_certificate.py
pulumi_checkly/dashboard.py
pulumi_checkly/dns_monitor.py
pulumi_checkly/environment_variable.py
pulumi_checkly/get_static_ips.py
pulumi_checkly/heartbeat_check.py
pulumi_checkly/heartbeat_monitor.py
pulumi_checkly/maintenance_window.py
pulumi_checkly/outputs.py
pulumi_checkly/private_location.py
pulumi_checkly/provider.py
pulumi_checkly/pulumi-plugin.json
pulumi_checkly/py.typed
pulumi_checkly/snippet.py
pulumi_checkly/status_page.py
pulumi_checkly/status_page_service.py
pulumi_checkly/tcp_check.py
pulumi_checkly/tcp_monitor.py
pulumi_checkly/trigger_check.py
pulumi_checkly/trigger_check_group.py
pulumi_checkly/url_monitor.py
pulumi_checkly/config/__init__.py
pulumi_checkly/config/__init__.pyi
pulumi_checkly/config/vars.py
pulumi_checkly-2.7.0.dist-info/METADATA
pulumi_checkly-2.7.0.dist-info/WHEEL
pulumi_checkly-2.7.0.dist-info/top_level.txt
pulumi_checkly-2.7.0.dist-info/RECORD
