Metadata-Version: 2.4
Name: pulumi_checkly
Version: 2.7.0
Summary: A Pulumi package for creating and managing Checkly monitoring resources.
License: Apache-2.0
Project-URL: Homepage, https://www.pulumi.com/registry/packages/checkly
Project-URL: Repository, https://github.com/checkly/pulumi-checkly
Keywords: pulumi,checkly,category/monitoring
Requires-Python: >=3.9
Requires-Dist: parver>=0.2.1
Requires-Dist: pulumi<4.0.0,>=3.0.0
Requires-Dist: semver>=2.8.1
Requires-Dist: typing-extensions<5,>=4.11; python_version < "3.11"
